tqdm_multi_thread/__init__.py
tqdm_multi_thread/tqdm_multi_thread.py
tqdm_multi_thread/tqdm_multi_thread_factory.py
tqdm_multi_thread-0.7.dist-info/LICENSE
tqdm_multi_thread-0.7.dist-info/METADATA
tqdm_multi_thread-0.7.dist-info/WHEEL
tqdm_multi_thread-0.7.dist-info/top_level.txt
tqdm_multi_thread-0.7.dist-info/RECORD
