Metadata-Version: 2.1
Name: tqdm-multi-thread
Version: 0.7
Summary: A tqdm multi-thread helper
Home-page: https://github.com/boydfd/tqdm_multi_thread
Author: Ran Lin
Author-email: boydfd@gmail.com
License: UNKNOWN
Platform: UNKNOWN
Classifier: Programming Language :: Python :: 3
Classifier: License :: OSI Approved :: MIT License
Classifier: Operating System :: OS Independent
Requires-Dist: tqdm
